Metadata-Version: 2.1
Name: ppmmvehicle
Version: 1.0.0
Summary: Ultralytics YOLOv8 for SOTA object detection, multi-object tracking, instance segmentation, pose estimation and image classification.
Home-page: https://github.com/ultralytics/ultralytics
Author: Ultralytics
Author-email: hello@ultralytics.com
License: AGPL-3.0
Project-URL: Bug Reports, https://github.com/ultralytics/ultralytics/issues
Project-URL: Funding, https://ultralytics.com
Project-URL: Source, https://github.com/ultralytics/ultralytics
Keywords: machine-learning,deep-learning,vision,ML,DL,AI,YOLO,YOLOv3,YOLOv5,YOLOv8,HUB,Ultralytics
Platform: UNKNOWN
Classifier: Development Status :: 4 - Beta
Classifier: Intended Audience :: Developers
Classifier: Intended Audience :: Education
Classifier: Intended Audience :: Science/Research
Classifier: License :: OSI Approved :: GNU Affero General Public License v3 or later (AGPLv3+)
Classifier: Programming Language :: Python :: 3
Classifier: Programming Language :: Python :: 3.7
Classifier: Programming Language :: Python :: 3.8
Classifier: Programming Language :: Python :: 3.9
Classifier: Programming Language :: Python :: 3.10
Classifier: Programming Language :: Python :: 3.11
Classifier: Topic :: Software Development
Classifier: Topic :: Scientific/Engineering
Classifier: Topic :: Scientific/Engineering :: Artificial Intelligence
Classifier: Topic :: Scientific/Engineering :: Image Recognition
Classifier: Operating System :: POSIX :: Linux
Classifier: Operating System :: MacOS
Classifier: Operating System :: Microsoft :: Windows
Requires-Python: >=3.7
Requires-Dist: matplotlib (>=3.2.2)
Requires-Dist: opencv-python (>=4.6.0)
Requires-Dist: Pillow (>=7.1.2)
Requires-Dist: PyYAML (>=5.3.1)
Requires-Dist: requests (>=2.23.0)
Requires-Dist: scipy (>=1.4.1)
Requires-Dist: torch (>=1.7.0)
Requires-Dist: torchvision (>=0.8.1)
Requires-Dist: tqdm (>=4.64.0)
Requires-Dist: pandas (>=1.1.4)
Requires-Dist: seaborn (>=0.11.0)
Requires-Dist: psutil
Provides-Extra: dev
Requires-Dist: check-manifest ; extra == 'dev'
Requires-Dist: pytest ; extra == 'dev'
Requires-Dist: pytest-cov ; extra == 'dev'
Requires-Dist: coverage ; extra == 'dev'
Requires-Dist: mkdocs-material ; extra == 'dev'
Requires-Dist: mkdocstrings[python] ; extra == 'dev'
Requires-Dist: mkdocs-redirects ; extra == 'dev'
Requires-Dist: mkdocs-ultralytics-plugin ; extra == 'dev'
Provides-Extra: export
Requires-Dist: coremltools (>=6.0) ; extra == 'export'
Requires-Dist: openvino-dev (>=2022.3) ; extra == 'export'
Requires-Dist: tensorflowjs ; extra == 'export'
